aicc_tools/__init__.py
aicc_tools/aicc_monitor.py
aicc_tools/ailog/__init__.py
aicc_tools/ailog/ailog_utils.py
aicc_tools/ailog/log.py
aicc_tools/ailog/redirect_stream.py
aicc_tools/cfts/__init__.py
aicc_tools/cfts/cfts.py
aicc_tools/utils/__init__.py
aicc_tools/utils/cloud_adapter.py
aicc_tools/utils/monitor.py
aicc_tools/utils/utils.py
aicc_tools/utils/validator.py
aicc_tools-0.2.1.dist-info/LICENSE
aicc_tools-0.2.1.dist-info/METADATA
aicc_tools-0.2.1.dist-info/WHEEL
aicc_tools-0.2.1.dist-info/top_level.txt
aicc_tools-0.2.1.dist-info/RECORD
