Metadata-Version: 2.1
Name: aicc-tools
Version: 0.2.1
Summary: aicc_tools is used of AI Computer Center for modelarts job.
Home-page: https://gitee.com/Lin-Bert/aicc.git
Author: Lin-Bert, zhangrui_wolf
Author-email: heqinglin4@huawei.com, zhangrui283@huawei.com
Classifier: Programming Language :: Python :: 3
Classifier: License :: OSI Approved :: MIT License
Classifier: Operating System :: OS Independent
Requires: numpy
Requires: mindspore
Requires: moxing
License-File: LICENSE
